README.rst
setup.py
dvent/__init__.py
dvent/aggregate.py
dvent/command.py
dvent/command_handler.py
dvent/event.py
dvent/event_store.py
dvent/repository.py
dvent.egg-info/PKG-INFO
dvent.egg-info/SOURCES.txt
dvent.egg-info/dependency_links.txt
dvent.egg-info/requires.txt
dvent.egg-info/top_level.txt