Metadata-Version: 1.2
Name: dvent
Version: 0.1.1
Summary: Simple, immutable, functional models for domain driven design with event sourcing
Home-page: https://github.com/jcrosen/dvent
Author: Jeremy Crosen
Author-email: jeremy.crosen@gmail.com
License: Apache License 2.0
Keywords: eventsourcing event sourcing ddd domain driven design immutable functional
Platform: UNKNOWN
Classifier: Development Status :: 4 - Beta
Classifier: Intended Audience :: Developers
Classifier: License :: OSI Approved :: Apache Software License
Classifier: Natural Language :: English
Classifier: Programming Language :: Python :: 3
Classifier: Programming Language :: Python :: 3.6
Classifier: Programming Language :: Python :: 3.5
Classifier: Programming Language :: Python :: 3.4
Classifier: Topic :: Software Development
Classifier: Topic :: Software Development :: Libraries
Requires-Python: >=3.4
